MANIFEST.in
chard.py
readme.md
setup.py
chard.egg-info/PKG-INFO
chard.egg-info/SOURCES.txt
chard.egg-info/dependency_links.txt
chard.egg-info/top_level.txt