Metadata-Version: 1.0
Name: chard
Version: 0
Summary: MongoDB Introspection-ish. ...
Home-page: https://github.com/uniphil/chard
Author: Phil Schleihauf
Author-email: uniphil@gmail.com
License: blah blah blah
Platform: UNKNOWN
